kenl380/__init__.py
kenl380/__version__.py
kenl380-1.0.0.dist-info/METADATA
kenl380-1.0.0.dist-info/RECORD
kenl380-1.0.0.dist-info/WHEEL
kenl380-1.0.0.dist-info/top_level.txt
