Metadata-Version: 2.1
Name: kenl380
Version: 1.0.0
Summary: Top Level Namespace Package for KenL380.
Home-page: https://github.com/kenlowrie/kenl380
Author: Ken Lowrie
Author-email: ken@kenlowrie.com
License: APACHE
Platform: UNKNOWN
Classifier: Development Status :: 5 - Production/Stable
Classifier: License :: OSI Approved :: Apache Software License
Classifier: Programming Language :: Python
Classifier: Programming Language :: Python :: 2.7
Classifier: Programming Language :: Python :: 3
Requires-Python: >=2.7
